{
    "tags": [],
    "description": "",
    "objects": [
        {
            "id": 818033332,
            "classId": 8907989,
            "description": "",
            "geometryType": "polygon",
            "labelerLogin": "juharrais1",
            "createdAt": "2021-08-03T17:45:49.547Z",
            "updatedAt": "2022-04-23T17:08:25.959Z",
            "tags": [],
            "classTitle": "Arvore",
            "points": {
                "exterior": [
                    [
                        0.0,
                        1148.0
                    ],
                    [
                        46.0,
                        1141.0
                    ],
                    [
                        85.0,
                        1143.0
                    ],
                    [
                        106.0,
                        1167.0
                    ],
                    [
                        127.0,
                        1190.0
                    ],
                    [
                        175.0,
                        1219.0
                    ],
                    [
                        205.0,
                        1247.0
                    ],
                    [
                        237.0,
                        1256.0
                    ],
                    [
                        276.0,
                        1287.0
                    ],
                    [
                        292.0,
                        1307.0
                    ],
                    [
                        304.0,
                        1325.0
                    ],
                    [
                        325.0,
                        1330.0
                    ],
                    [
                        334.0,
                        1351.0
                    ],
                    [
                        341.0,
                        1378.0
                    ],
                    [
                        375.0,
                        1385.0
                    ],
                    [
                        417.0,
                        1392.0
                    ],
                    [
                        444.0,
                        1413.0
                    ],
                    [
                        472.0,
                        1408.0
                    ],
                    [
                        493.0,
                        1378.0
                    ],
                    [
                        483.0,
                        1344.0
                    ],
                    [
                        474.0,
                        1314.0
                    ],
                    [
                        509.0,
                        1263.0
                    ],
                    [
                        566.0,
                        1222.0
                    ],
                    [
                        605.0,
                        1213.0
                    ],
                    [
                        658.0,
                        1210.0
                    ],
                    [
                        697.0,
                        1229.0
                    ],
                    [
                        711.0,
                        1270.0
                    ],
                    [
                        721.0,
                        1309.0
                    ],
                    [
                        723.0,
                        1376.0
                    ],
                    [
                        707.0,
                        1406.0
                    ],
                    [
                        693.0,
                        1466.0
                    ],
                    [
                        684.0,
                        1532.0
                    ],
                    [
                        691.0,
                        1585.0
                    ],
                    [
                        716.0,
                        1608.0
                    ],
                    [
                        741.0,
                        1608.0
                    ],
                    [
                        753.0,
                        1562.0
                    ],
                    [
                        771.0,
                        1505.0
                    ],
                    [
                        773.0,
                        1450.0
                    ],
                    [
                        833.0,
                        1413.0
                    ],
                    [
                        868.0,
                        1374.0
                    ],
                    [
                        891.0,
                        1367.0
                    ],
                    [
                        884.0,
                        1323.0
                    ],
                    [
                        847.0,
                        1288.0
                    ],
                    [
                        836.0,
                        1240.0
                    ],
                    [
                        836.0,
                        1208.0
                    ],
                    [
                        845.0,
                        1187.0
                    ],
                    [
                        900.0,
                        1242.0
                    ],
                    [
                        902.0,
                        1222.0
                    ],
                    [
                        902.0,
                        1146.0
                    ],
                    [
                        921.0,
                        1141.0
                    ],
                    [
                        895.0,
                        1093.0
                    ],
                    [
                        898.0,
                        1054.0
                    ],
                    [
                        928.0,
                        1054.0
                    ],
                    [
                        1013.0,
                        1070.0
                    ],
                    [
                        1031.0,
                        1072.0
                    ],
                    [
                        1077.0,
                        1116.0
                    ],
                    [
                        1084.0,
                        1150.0
                    ],
                    [
                        1087.0,
                        1190.0
                    ],
                    [
                        1105.0,
                        1224.0
                    ],
                    [
                        1112.0,
                        1242.0
                    ],
                    [
                        1121.0,
                        1284.0
                    ],
                    [
                        1121.0,
                        1314.0
                    ],
                    [
                        1123.0,
                        1335.0
                    ],
                    [
                        1160.0,
                        1360.0
                    ],
                    [
                        1188.0,
                        1332.0
                    ],
                    [
                        1215.0,
                        1288.0
                    ],
                    [
                        1261.0,
                        1263.0
                    ],
                    [
                        1291.0,
                        1268.0
                    ],
                    [
                        1328.0,
                        1318.0
                    ],
                    [
                        1352.0,
                        1362.0
                    ],
                    [
                        1379.0,
                        1383.0
                    ],
                    [
                        1413.0,
                        1383.0
                    ],
                    [
                        1441.0,
                        1408.0
                    ],
                    [
                        1478.0,
                        1397.0
                    ],
                    [
                        1494.0,
                        1374.0
                    ],
                    [
                        1531.0,
                        1353.0
                    ],
                    [
                        1565.0,
                        1360.0
                    ],
                    [
                        1565.0,
                        1387.0
                    ],
                    [
                        1561.0,
                        1434.0
                    ],
                    [
                        1593.0,
                        1450.0
                    ],
                    [
                        1623.0,
                        1440.0
                    ],
                    [
                        1637.0,
                        1406.0
                    ],
                    [
                        1662.0,
                        1341.0
                    ],
                    [
                        1676.0,
                        1323.0
                    ],
                    [
                        1694.0,
                        1339.0
                    ],
                    [
                        1706.0,
                        1362.0
                    ],
                    [
                        1726.0,
                        1362.0
                    ],
                    [
                        1759.0,
                        1353.0
                    ],
                    [
                        1779.0,
                        1360.0
                    ],
                    [
                        1786.0,
                        1383.0
                    ],
                    [
                        1849.0,
                        1366.0
                    ],
                    [
                        1890.0,
                        1353.0
                    ],
                    [
                        1913.0,
                        1346.0
                    ],
                    [
                        1945.0,
                        1351.0
                    ],
                    [
                        1984.0,
                        1394.0
                    ],
                    [
                        2005.0,
                        1422.0
                    ],
                    [
                        2030.0,
                        1417.0
                    ],
                    [
                        2106.0,
                        1369.0
                    ],
                    [
                        2129.0,
                        1376.0
                    ],
                    [
                        2148.0,
                        1374.0
                    ],
                    [
                        2180.0,
                        1348.0
                    ],
                    [
                        2189.0,
                        1314.0
                    ],
                    [
                        2185.0,
                        1268.0
                    ],
                    [
                        2187.0,
                        1213.0
                    ],
                    [
                        2189.0,
                        1190.0
                    ],
                    [
                        2219.0,
                        1226.0
                    ],
                    [
                        2231.0,
                        1272.0
                    ],
                    [
                        2231.0,
                        1199.0
                    ],
                    [
                        2263.0,
                        1215.0
                    ],
                    [
                        2277.0,
                        1272.0
                    ],
                    [
                        2281.0,
                        1162.0
                    ],
                    [
                        2311.0,
                        1201.0
                    ],
                    [
                        2327.0,
                        1254.0
                    ],
                    [
                        2339.0,
                        1302.0
                    ],
                    [
                        2364.0,
                        1335.0
                    ],
                    [
                        2387.0,
                        1279.0
                    ],
                    [
                        2376.0,
                        1231.0
                    ],
                    [
                        2426.0,
                        1226.0
                    ],
                    [
                        2488.0,
                        1247.0
                    ],
                    [
                        2472.0,
                        1291.0
                    ],
                    [
                        2465.0,
                        1314.0
                    ],
                    [
                        2523.0,
                        1273.0
                    ],
                    [
                        2555.0,
                        1337.0
                    ],
                    [
                        2583.0,
                        1351.0
                    ],
                    [
                        2591.0,
                        1343.0
                    ],
                    [
                        2591.0,
                        1943.0
                    ],
                    [
                        0.0,
                        1943.0
                    ]
                ],
                "interior": []
            }
        },
        {
            "id": 818033331,
            "classId": 8907991,
            "description": "",
            "geometryType": "polygon",
            "labelerLogin": "juharrais1",
            "createdAt": "2021-08-03T17:45:49.547Z",
            "updatedAt": "2022-04-23T17:08:25.959Z",
            "tags": [],
            "classTitle": "Estratiformes",
            "points": {
                "exterior": [
                    [
                        0.0,
                        692.0
                    ],
                    [
                        67.0,
                        738.0
                    ],
                    [
                        97.0,
                        752.0
                    ],
                    [
                        164.0,
                        814.0
                    ],
                    [
                        184.0,
                        830.0
                    ],
                    [
                        219.0,
                        821.0
                    ],
                    [
                        299.0,
                        750.0
                    ],
                    [
                        320.0,
                        750.0
                    ],
                    [
                        364.0,
                        738.0
                    ],
                    [
                        315.0,
                        729.0
                    ],
                    [
                        249.0,
                        722.0
                    ],
                    [
                        198.0,
                        699.0
                    ],
                    [
                        157.0,
                        653.0
                    ],
                    [
                        267.0,
                        626.0
                    ],
                    [
                        352.0,
                        669.0
                    ],
                    [
                        387.0,
                        674.0
                    ],
                    [
                        474.0,
                        708.0
                    ],
                    [
                        516.0,
                        738.0
                    ],
                    [
                        592.0,
                        743.0
                    ],
                    [
                        658.0,
                        771.0
                    ],
                    [
                        686.0,
                        807.0
                    ],
                    [
                        797.0,
                        856.0
                    ],
                    [
                        889.0,
                        870.0
                    ],
                    [
                        944.0,
                        881.0
                    ],
                    [
                        928.0,
                        844.0
                    ],
                    [
                        845.0,
                        824.0
                    ],
                    [
                        801.0,
                        798.0
                    ],
                    [
                        767.0,
                        771.0
                    ],
                    [
                        748.0,
                        725.0
                    ],
                    [
                        750.0,
                        702.0
                    ],
                    [
                        776.0,
                        683.0
                    ],
                    [
                        831.0,
                        665.0
                    ],
                    [
                        863.0,
                        644.0
                    ],
                    [
                        946.0,
                        616.0
                    ],
                    [
                        1008.0,
                        614.0
                    ],
                    [
                        1057.0,
                        616.0
                    ],
                    [
                        1123.0,
                        656.0
                    ],
                    [
                        1146.0,
                        665.0
                    ],
                    [
                        1260.0,
                        706.0
                    ],
                    [
                        1358.0,
                        748.0
                    ],
                    [
                        1386.0,
                        777.0
                    ],
                    [
                        1416.0,
                        828.0
                    ],
                    [
                        1453.0,
                        870.0
                    ],
                    [
                        1466.0,
                        890.0
                    ],
                    [
                        1455.0,
                        918.0
                    ],
                    [
                        1379.0,
                        948.0
                    ],
                    [
                        1287.0,
                        955.0
                    ],
                    [
                        1215.0,
                        966.0
                    ],
                    [
                        1160.0,
                        980.0
                    ],
                    [
                        1190.0,
                        989.0
                    ],
                    [
                        1245.0,
                        1008.0
                    ],
                    [
                        1305.0,
                        1008.0
                    ],
                    [
                        1377.0,
                        1001.0
                    ],
                    [
                        1459.0,
                        996.0
                    ],
                    [
                        1524.0,
                        987.0
                    ],
                    [
                        1655.0,
                        978.0
                    ],
                    [
                        1683.0,
                        962.0
                    ],
                    [
                        1752.0,
                        943.0
                    ],
                    [
                        1821.0,
                        946.0
                    ],
                    [
                        1871.0,
                        950.0
                    ],
                    [
                        1908.0,
                        950.0
                    ],
                    [
                        1973.0,
                        934.0
                    ],
                    [
                        2026.0,
                        909.0
                    ],
                    [
                        2076.0,
                        918.0
                    ],
                    [
                        2102.0,
                        916.0
                    ],
                    [
                        2152.0,
                        902.0
                    ],
                    [
                        2221.0,
                        904.0
                    ],
                    [
                        2288.0,
                        906.0
                    ],
                    [
                        2350.0,
                        897.0
                    ],
                    [
                        2422.0,
                        881.0
                    ],
                    [
                        2488.0,
                        863.0
                    ],
                    [
                        2546.0,
                        856.0
                    ],
                    [
                        2580.0,
                        853.0
                    ],
                    [
                        2591.0,
                        853.0
                    ],
                    [
                        2591.0,
                        1344.0
                    ],
                    [
                        2571.0,
                        1339.0
                    ],
                    [
                        2550.0,
                        1275.0
                    ],
                    [
                        2530.0,
                        1279.0
                    ],
                    [
                        2506.0,
                        1312.0
                    ],
                    [
                        2488.0,
                        1316.0
                    ],
                    [
                        2495.0,
                        1270.0
                    ],
                    [
                        2498.0,
                        1249.0
                    ],
                    [
                        2472.0,
                        1231.0
                    ],
                    [
                        2447.0,
                        1222.0
                    ],
                    [
                        2419.0,
                        1222.0
                    ],
                    [
                        2380.0,
                        1248.0
                    ],
                    [
                        2392.0,
                        1295.0
                    ],
                    [
                        2350.0,
                        1348.0
                    ],
                    [
                        2357.0,
                        1312.0
                    ],
                    [
                        2339.0,
                        1286.0
                    ],
                    [
                        2332.0,
                        1261.0
                    ],
                    [
                        2332.0,
                        1208.0
                    ],
                    [
                        2311.0,
                        1173.0
                    ],
                    [
                        2298.0,
                        1199.0
                    ],
                    [
                        2293.0,
                        1224.0
                    ],
                    [
                        2288.0,
                        1245.0
                    ],
                    [
                        2251.0,
                        1194.0
                    ],
                    [
                        2235.0,
                        1226.0
                    ],
                    [
                        2233.0,
                        1259.0
                    ],
                    [
                        2207.0,
                        1215.0
                    ],
                    [
                        2175.0,
                        1206.0
                    ],
                    [
                        2168.0,
                        1238.0
                    ],
                    [
                        2175.0,
                        1298.0
                    ],
                    [
                        2175.0,
                        1335.0
                    ],
                    [
                        2171.0,
                        1362.0
                    ],
                    [
                        2148.0,
                        1376.0
                    ],
                    [
                        2060.0,
                        1399.0
                    ],
                    [
                        2039.0,
                        1406.0
                    ],
                    [
                        2007.0,
                        1408.0
                    ],
                    [
                        1961.0,
                        1387.0
                    ],
                    [
                        1927.0,
                        1351.0
                    ],
                    [
                        1901.0,
                        1351.0
                    ],
                    [
                        1823.0,
                        1360.0
                    ],
                    [
                        1786.0,
                        1378.0
                    ],
                    [
                        1756.0,
                        1341.0
                    ],
                    [
                        1724.0,
                        1348.0
                    ],
                    [
                        1703.0,
                        1335.0
                    ],
                    [
                        1655.0,
                        1335.0
                    ],
                    [
                        1646.0,
                        1364.0
                    ],
                    [
                        1641.0,
                        1408.0
                    ],
                    [
                        1614.0,
                        1438.0
                    ],
                    [
                        1602.0,
                        1459.0
                    ],
                    [
                        1581.0,
                        1431.0
                    ],
                    [
                        1563.0,
                        1385.0
                    ],
                    [
                        1552.0,
                        1353.0
                    ],
                    [
                        1515.0,
                        1353.0
                    ],
                    [
                        1492.0,
                        1353.0
                    ],
                    [
                        1476.0,
                        1371.0
                    ],
                    [
                        1455.0,
                        1390.0
                    ],
                    [
                        1416.0,
                        1408.0
                    ],
                    [
                        1395.0,
                        1387.0
                    ],
                    [
                        1377.0,
                        1383.0
                    ],
                    [
                        1363.0,
                        1362.0
                    ],
                    [
                        1340.0,
                        1328.0
                    ],
                    [
                        1321.0,
                        1295.0
                    ],
                    [
                        1305.0,
                        1270.0
                    ],
                    [
                        1287.0,
                        1261.0
                    ],
                    [
                        1257.0,
                        1268.0
                    ],
                    [
                        1234.0,
                        1284.0
                    ],
                    [
                        1199.0,
                        1312.0
                    ],
                    [
                        1177.0,
                        1332.0
                    ],
                    [
                        1142.0,
                        1362.0
                    ],
                    [
                        1123.0,
                        1330.0
                    ],
                    [
                        1103.0,
                        1275.0
                    ],
                    [
                        1100.0,
                        1226.0
                    ],
                    [
                        1080.0,
                        1192.0
                    ],
                    [
                        1070.0,
                        1157.0
                    ],
                    [
                        1079.0,
                        1113.0
                    ],
                    [
                        1036.0,
                        1083.0
                    ],
                    [
                        1001.0,
                        1068.0
                    ],
                    [
                        967.0,
                        1065.0
                    ],
                    [
                        946.0,
                        1061.0
                    ],
                    [
                        911.0,
                        1071.0
                    ],
                    [
                        900.0,
                        1100.0
                    ],
                    [
                        909.0,
                        1125.0
                    ],
                    [
                        921.0,
                        1143.0
                    ],
                    [
                        882.0,
                        1155.0
                    ],
                    [
                        905.0,
                        1187.0
                    ],
                    [
                        907.0,
                        1222.0
                    ],
                    [
                        909.0,
                        1245.0
                    ],
                    [
                        877.0,
                        1231.0
                    ],
                    [
                        842.0,
                        1206.0
                    ],
                    [
                        845.0,
                        1233.0
                    ],
                    [
                        870.0,
                        1286.0
                    ],
                    [
                        891.0,
                        1346.0
                    ],
                    [
                        875.0,
                        1378.0
                    ],
                    [
                        854.0,
                        1390.0
                    ],
                    [
                        808.0,
                        1429.0
                    ],
                    [
                        773.0,
                        1463.0
                    ],
                    [
                        769.0,
                        1503.0
                    ],
                    [
                        766.0,
                        1565.0
                    ],
                    [
                        739.0,
                        1608.0
                    ],
                    [
                        711.0,
                        1592.0
                    ],
                    [
                        702.0,
                        1562.0
                    ],
                    [
                        702.0,
                        1496.0
                    ],
                    [
                        711.0,
                        1440.0
                    ],
                    [
                        721.0,
                        1385.0
                    ],
                    [
                        721.0,
                        1325.0
                    ],
                    [
                        721.0,
                        1286.0
                    ],
                    [
                        688.0,
                        1233.0
                    ],
                    [
                        665.0,
                        1226.0
                    ],
                    [
                        628.0,
                        1217.0
                    ],
                    [
                        599.0,
                        1215.0
                    ],
                    [
                        564.0,
                        1219.0
                    ],
                    [
                        541.0,
                        1240.0
                    ],
                    [
                        511.0,
                        1259.0
                    ],
                    [
                        488.0,
                        1302.0
                    ],
                    [
                        479.0,
                        1334.0
                    ],
                    [
                        483.0,
                        1371.0
                    ],
                    [
                        486.0,
                        1392.0
                    ],
                    [
                        465.0,
                        1397.0
                    ],
                    [
                        419.0,
                        1399.0
                    ],
                    [
                        375.0,
                        1381.0
                    ],
                    [
                        343.0,
                        1371.0
                    ],
                    [
                        315.0,
                        1335.0
                    ],
                    [
                        299.0,
                        1316.0
                    ],
                    [
                        279.0,
                        1298.0
                    ],
                    [
                        258.0,
                        1277.0
                    ],
                    [
                        205.0,
                        1242.0
                    ],
                    [
                        177.0,
                        1213.0
                    ],
                    [
                        138.0,
                        1194.0
                    ],
                    [
                        102.0,
                        1169.0
                    ],
                    [
                        65.0,
                        1155.0
                    ],
                    [
                        0.0,
                        1153.0
                    ],
                    [
                        0.0,
                        1153.0
                    ]
                ],
                "interior": [
                    [
                        [
                            642.0,
                            1153.0
                        ],
                        [
                            608.0,
                            1153.0
                        ],
                        [
                            534.0,
                            1146.0
                        ],
                        [
                            493.0,
                            1132.0
                        ],
                        [
                            474.0,
                            1118.0
                        ],
                        [
                            550.0,
                            1107.0
                        ],
                        [
                            605.0,
                            1109.0
                        ],
                        [
                            633.0,
                            1134.0
                        ]
                    ],
                    [
                        [
                            1112.0,
                            1024.0
                        ],
                        [
                            1087.0,
                            1024.0
                        ],
                        [
                            1056.0,
                            999.0
                        ],
                        [
                            1100.0,
                            982.0
                        ],
                        [
                            1119.0,
                            1001.0
                        ],
                        [
                            1123.0,
                            1005.0
                        ]
                    ]
                ]
            }
        },
        {
            "id": 818033330,
            "classId": 8907990,
            "description": "",
            "geometryType": "polygon",
            "labelerLogin": "juharrais1",
            "createdAt": "2021-08-03T17:45:49.547Z",
            "updatedAt": "2022-04-23T17:08:25.959Z",
            "tags": [],
            "classTitle": "Estratocumuliformes",
            "points": {
                "exterior": [
                    [
                        1282.0,
                        0.0
                    ],
                    [
                        2373.0,
                        0.0
                    ],
                    [
                        2399.0,
                        0.0
                    ],
                    [
                        2458.0,
                        62.0
                    ],
                    [
                        2495.0,
                        133.0
                    ],
                    [
                        2493.0,
                        80.0
                    ],
                    [
                        2491.0,
                        52.0
                    ],
                    [
                        2484.0,
                        25.0
                    ],
                    [
                        2426.0,
                        4.0
                    ],
                    [
                        2591.0,
                        0.0
                    ],
                    [
                        2591.0,
                        243.0
                    ],
                    [
                        2585.0,
                        260.0
                    ],
                    [
                        2548.0,
                        266.0
                    ],
                    [
                        2537.0,
                        296.0
                    ],
                    [
                        2560.0,
                        292.0
                    ],
                    [
                        2591.0,
                        292.0
                    ],
                    [
                        2591.0,
                        429.0
                    ],
                    [
                        2550.0,
                        462.0
                    ],
                    [
                        2562.0,
                        483.0
                    ],
                    [
                        2591.0,
                        485.0
                    ],
                    [
                        2578.0,
                        688.0
                    ],
                    [
                        2564.0,
                        708.0
                    ],
                    [
                        2580.0,
                        734.0
                    ],
                    [
                        2591.0,
                        794.0
                    ],
                    [
                        2585.0,
                        805.0
                    ],
                    [
                        2532.0,
                        817.0
                    ],
                    [
                        2491.0,
                        812.0
                    ],
                    [
                        2458.0,
                        782.0
                    ],
                    [
                        2408.0,
                        752.0
                    ],
                    [
                        2362.0,
                        745.0
                    ],
                    [
                        2272.0,
                        745.0
                    ],
                    [
                        2237.0,
                        780.0
                    ],
                    [
                        2254.0,
                        803.0
                    ],
                    [
                        2288.0,
                        798.0
                    ],
                    [
                        2332.0,
                        773.0
                    ],
                    [
                        2392.0,
                        771.0
                    ],
                    [
                        2417.0,
                        814.0
                    ],
                    [
                        2399.0,
                        840.0
                    ],
                    [
                        2367.0,
                        851.0
                    ],
                    [
                        2323.0,
                        881.0
                    ],
                    [
                        2281.0,
                        886.0
                    ],
                    [
                        2237.0,
                        893.0
                    ],
                    [
                        2189.0,
                        895.0
                    ],
                    [
                        2132.0,
                        895.0
                    ],
                    [
                        2102.0,
                        897.0
                    ],
                    [
                        2056.0,
                        911.0
                    ],
                    [
                        1992.0,
                        925.0
                    ],
                    [
                        1931.0,
                        923.0
                    ],
                    [
                        1897.0,
                        929.0
                    ],
                    [
                        1878.0,
                        943.0
                    ],
                    [
                        1849.0,
                        950.0
                    ],
                    [
                        1777.0,
                        932.0
                    ],
                    [
                        1733.0,
                        913.0
                    ],
                    [
                        1690.0,
                        904.0
                    ],
                    [
                        1639.0,
                        895.0
                    ],
                    [
                        1600.0,
                        888.0
                    ],
                    [
                        1563.0,
                        863.0
                    ],
                    [
                        1528.0,
                        858.0
                    ],
                    [
                        1489.0,
                        844.0
                    ],
                    [
                        1464.0,
                        837.0
                    ],
                    [
                        1390.0,
                        803.0
                    ],
                    [
                        1388.0,
                        761.0
                    ],
                    [
                        1434.0,
                        748.0
                    ],
                    [
                        1450.0,
                        722.0
                    ],
                    [
                        1443.0,
                        686.0
                    ],
                    [
                        1414.0,
                        637.0
                    ],
                    [
                        1372.0,
                        619.0
                    ],
                    [
                        1331.0,
                        614.0
                    ],
                    [
                        1289.0,
                        614.0
                    ],
                    [
                        1241.0,
                        614.0
                    ],
                    [
                        1215.0,
                        614.0
                    ],
                    [
                        1169.0,
                        582.0
                    ],
                    [
                        1142.0,
                        573.0
                    ],
                    [
                        1084.0,
                        536.0
                    ],
                    [
                        1034.0,
                        527.0
                    ],
                    [
                        997.0,
                        527.0
                    ],
                    [
                        946.0,
                        522.0
                    ],
                    [
                        847.0,
                        458.0
                    ],
                    [
                        833.0,
                        416.0
                    ],
                    [
                        914.0,
                        416.0
                    ],
                    [
                        990.0,
                        409.0
                    ],
                    [
                        1031.0,
                        379.0
                    ],
                    [
                        994.0,
                        363.0
                    ],
                    [
                        958.0,
                        331.0
                    ],
                    [
                        981.0,
                        276.0
                    ],
                    [
                        1011.0,
                        269.0
                    ],
                    [
                        1080.0,
                        290.0
                    ],
                    [
                        1128.0,
                        324.0
                    ],
                    [
                        1167.0,
                        361.0
                    ],
                    [
                        1211.0,
                        345.0
                    ],
                    [
                        1236.0,
                        301.0
                    ],
                    [
                        1167.0,
                        260.0
                    ],
                    [
                        1142.0,
                        216.0
                    ],
                    [
                        1202.0,
                        163.0
                    ],
                    [
                        1250.0,
                        144.0
                    ],
                    [
                        1275.0,
                        108.0
                    ],
                    [
                        1275.0,
                        64.0
                    ],
                    [
                        1275.0,
                        41.0
                    ]
                ],
                "interior": [
                    [
                        [
                            2111.0,
                            623.0
                        ],
                        [
                            2129.0,
                            614.0
                        ],
                        [
                            2118.0,
                            573.0
                        ],
                        [
                            2099.0,
                            577.0
                        ],
                        [
                            2079.0,
                            609.0
                        ],
                        [
                            2086.0,
                            628.0
                        ]
                    ],
                    [
                        [
                            1749.0,
                            554.0
                        ],
                        [
                            1756.0,
                            534.0
                        ],
                        [
                            1738.0,
                            512.0
                        ],
                        [
                            1660.0,
                            492.0
                        ],
                        [
                            1611.0,
                            510.0
                        ],
                        [
                            1579.0,
                            586.0
                        ],
                        [
                            1604.0,
                            586.0
                        ],
                        [
                            1644.0,
                            577.0
                        ],
                        [
                            1729.0,
                            573.0
                        ]
                    ],
                    [
                        [
                            1980.0,
                            290.0
                        ],
                        [
                            1993.0,
                            260.0
                        ],
                        [
                            1975.0,
                            250.0
                        ],
                        [
                            1954.0,
                            250.0
                        ],
                        [
                            1931.0,
                            264.0
                        ],
                        [
                            1924.0,
                            301.0
                        ]
                    ],
                    [
                        [
                            2320.0,
                            158.0
                        ],
                        [
                            2346.0,
                            133.0
                        ],
                        [
                            2313.0,
                            140.0
                        ],
                        [
                            2290.0,
                            161.0
                        ]
                    ]
                ]
            }
        },
        {
            "id": 818033329,
            "classId": 8907990,
            "description": "",
            "geometryType": "polygon",
            "labelerLogin": "juharrais1",
            "createdAt": "2021-08-03T17:45:49.547Z",
            "updatedAt": "2022-04-23T17:08:25.959Z",
            "tags": [],
            "classTitle": "Estratocumuliformes",
            "points": {
                "exterior": [
                    [
                        13.0,
                        6.0
                    ],
                    [
                        322.0,
                        34.0
                    ],
                    [
                        377.0,
                        114.0
                    ],
                    [
                        475.0,
                        132.0
                    ],
                    [
                        528.0,
                        164.0
                    ],
                    [
                        601.0,
                        173.0
                    ],
                    [
                        643.0,
                        207.0
                    ],
                    [
                        688.0,
                        246.0
                    ],
                    [
                        677.0,
                        276.0
                    ],
                    [
                        661.0,
                        308.0
                    ],
                    [
                        620.0,
                        340.0
                    ],
                    [
                        519.0,
                        372.0
                    ],
                    [
                        448.0,
                        375.0
                    ],
                    [
                        345.0,
                        349.0
                    ],
                    [
                        276.0,
                        353.0
                    ],
                    [
                        275.0,
                        420.0
                    ],
                    [
                        178.0,
                        413.0
                    ],
                    [
                        150.0,
                        397.0
                    ],
                    [
                        57.0,
                        347.0
                    ],
                    [
                        11.0,
                        320.0
                    ],
                    [
                        0.0,
                        316.0
                    ]
                ],
                "interior": []
            }
        },
        {
            "id": 818033328,
            "classId": 8907990,
            "description": "",
            "geometryType": "polygon",
            "labelerLogin": "juharrais1",
            "createdAt": "2021-08-03T17:45:49.547Z",
            "updatedAt": "2022-04-23T17:08:25.959Z",
            "tags": [],
            "classTitle": "Estratocumuliformes",
            "points": {
                "exterior": [
                    [
                        791.0,
                        45.0
                    ],
                    [
                        826.0,
                        221.0
                    ],
                    [
                        846.0,
                        260.0
                    ],
                    [
                        919.0,
                        285.0
                    ],
                    [
                        1032.0,
                        283.0
                    ],
                    [
                        1103.0,
                        288.0
                    ],
                    [
                        1141.0,
                        256.0
                    ],
                    [
                        1141.0,
                        224.0
                    ],
                    [
                        1187.0,
                        153.0
                    ],
                    [
                        1238.0,
                        114.0
                    ],
                    [
                        1274.0,
                        50.0
                    ],
                    [
                        1251.0,
                        13.0
                    ],
                    [
                        878.0,
                        11.0
                    ],
                    [
                        860.0,
                        15.0
                    ]
                ],
                "interior": []
            }
        }
    ],
    "size": {
        "height": 1944,
        "width": 2592
    }
}